LICENSE
MANIFEST.in
README.md
VERSION
setup.py
doppel/DoppelTestError.py
doppel/PackageAPI.py
doppel/PackageCollection.py
doppel/__init__.py
doppel/cli.py
doppel/describe.py
doppel/reporters.py
doppel/bin/analyze.R
doppel/bin/analyze.py
doppel_cli.egg-info/PKG-INFO
doppel_cli.egg-info/SOURCES.txt
doppel_cli.egg-info/dependency_links.txt
doppel_cli.egg-info/entry_points.txt
doppel_cli.egg-info/requires.txt
doppel_cli.egg-info/top_level.txt
tests/__init__.py
tests/test_DoppelTestError.py
tests/test_package_api.py
tests/test_package_collection.py
tests/test_reporters.py