Metadata-Version: 2.1
Name: doppel-cli
Version: 0.2.1
Summary: An integration testing framework for testing API similarity of software libraries.
Home-page: http://github.com/jameslamb/doppel-cli
Maintainer: James Lamb
Maintainer-email: jaylamb20@gmail.com
License: BSD 3-clause
Platform: UNKNOWN
Classifier: Development Status :: 3 - Alpha
Classifier: Intended Audience :: Developers
Classifier: License :: OSI Approved :: BSD License
Classifier: Programming Language :: Python
Classifier: Programming Language :: Python :: 3
Classifier: Programming Language :: Python :: 3.5
Classifier: Programming Language :: Python :: 3.6
Classifier: Topic :: Software Development :: Testing
Provides-Extra: docs
Provides-Extra: testing
Provides-Extra: all
